multi_rename/__init__.py
multi_rename/renamer.py
tests/__init__.py
tests/test_renamer.py
multi_rename-0.0.4.dist-info/LICENSE
multi_rename-0.0.4.dist-info/METADATA
multi_rename-0.0.4.dist-info/WHEEL
multi_rename-0.0.4.dist-info/top_level.txt
multi_rename-0.0.4.dist-info/RECORD
