Metadata-Version: 2.1
Name: multi-rename
Version: 0.0.4
Summary: Easily rename multiple files ending with incrementing numbers.
Home-page: https://github.com/pshkrh/multi-rename
Author: Pushkar Kurhekar
Author-email: contact@pshkrh.com
License: UNKNOWN
Keywords: multi batch rename all files
Platform: UNKNOWN
Classifier: Programming Language :: Python :: 3
Classifier: License :: OSI Approved :: MIT License
Classifier: Operating System :: OS Independent
Classifier: Development Status :: 3 - Alpha
Classifier: Intended Audience :: Developers
Requires-Python: >=3.3
